{
  "resourceType" : "ValueSet",
  "id" : "2b3a5a0a-d450-4eba-bcdc-c44ef7930ce3-647",
  "url" : "http://hl7.org/fhir/comparison/ValueSet/2b3a5a0a-d450-4eba-bcdc-c44ef7930ce3-647",
  "name" : "UnionHIVDDE391AndHIVDDE391",
  "title" : "Union of Reason for HIV viral load test ValueSet And Reason for HIV viral load test ValueSet",
  "status" : "active",
  "date" : "2026-03-05T13:14:02+00:00",
  "compose" : {
    "include" : [{
      "concept" : [{
        "code" : "HIV.D.DE392",
        "display" : "Routine viral load test"
      },
      {
        "code" : "HIV.D.DE393",
        "display" : "Targeted viral load monitoring"
      },
      {
        "code" : "HIV.D.DE394",
        "display" : "Initial viral load test"
      },
      {
        "code" : "HIV.D.DE395",
        "display" : "Follow-up viral load test after receiving enhanced adherence counselling"
      }]
    }]
  }
}